Metadata-Version: 2.1
Name: ast-refactor
Version: 0.1.0
Summary: Transform code using the power of the Python AST
Home-page: https://github.com/flatironhealth/ast-refactor
Author: Flatiron Health Data Tooling
Author-email: data-tooling@flatiron.com
License: BSD-3-Clause
Platform: UNKNOWN
Classifier: Programming Language :: Python :: 3 :: Only
Classifier: License :: OSI Approved :: BSD License
Classifier: Operating System :: OS Independent
Requires-Python: >=3.6
